README
setup.py
portunhol/__init__.py
portunhol/main.py
portunhol/portunhol.py
portunhol/web_server.py
portunhol/web_server_get.py
portunhol.egg-info/PKG-INFO
portunhol.egg-info/SOURCES.txt
portunhol.egg-info/dependency_links.txt
portunhol.egg-info/not-zip-safe
portunhol.egg-info/top_level.txt