Metadata-Version: 1.0
Name: portunhol
Version: 0.2
Summary: A translator from portuguse to portunhol
Home-page: https://github.com/belimawr/portunhol/
Author: Tiago Queiroz
Author-email: contato@tiago.eti.br
License: GPLv3
Platform: UNKNOWN
